{
    "4月13日": [
        "G2",
        "数Ⅱ S/La",
        "E2",
        "現代文",
        "A2"
    ],
    "4月14日": [
        "A2",
        "E2",
        "英語W",
        "K2",
        "英語長文"
    ],
    "4月15日": [
        "K1",
        "G1",
        "英語R",
        "英語Wt",
        "数Ⅱ S/Lb"
    ],
    "4月16日": [
        "古典",
        "G2",
        "体育別修",
        "K1",
        "HR"
    ],
    "4月17日": [
        "現代文",
        "E1",
        "A1",
        "英語R",
        "数Ⅱ S/La"
    ],
    "4月18日": [
        "数Ⅱ S/Lb",
        "英語長文",
        "体育共修"
    ],
    "4月20日": [
        "K2",
        "数Ⅱ S/La",
        "英語長文",
        "G1",
        "E2"
    ],
    "4月21日": [
        "A2",
        "E1",
        "IBA Ⅳ",
        "K2",
        "古典"
    ],
    "4月22日": [
        "G1",
        "数Ⅱ S/Lb",
        "K1",
        "体育別修",
        "英語R"
    ],
    "4月23日": [
        "古典",
        "現代文",
        "A1",
        "体育共修",
        "HR"
    ],
    "4月24日": [
        "数Ⅱ S/La",
        "E1",
        "A1",
        "英語W",
        "G2"
    ],
    "4月27日": [
        "G2",
        "数Ⅱ S/La",
        "E2",
        "現代文",
        "A2"
    ],
    "4月28日": [
        "A2",
        "E2",
        "英語W",
        "K2",
        "英語長文"
    ],
    "4月30日": [
        "古典",
        "G2",
        "体育別修",
        "K1",
        "HR"
    ],
    "5月1日": [
        "現代文",
        "E1",
        "A1",
        "英語R",
        "数Ⅱ S/La"
    ],
    "5月7日": [
        "K1",
        "G1",
        "英語R"
    ],
    "5月9日": [
        "数Ⅱ S/Lb",
        "体育共修",
        "古典"
    ],
    "5月11日": [
        "K2",
        "数Ⅱ S/La",
        "英語長文",
        "G1",
        "E2"
    ],
    "5月12日": [
        "A2",
        "E1",
        "IBA Ⅳ",
        "K2",
        "古典"
    ],
    "5月13日": [
        "G1",
        "数Ⅱ S/Lb",
        "K1",
        "体育別修",
        "英語R"
    ],
    "5月14日": [
        "古典",
        "現代文",
        "A1",
        "体育共修",
        "HR"
    ],
    "5月15日": [
        "数Ⅱ S/La",
        "E1",
        "A1",
        "英語W",
        "G2"
    ],
    "5月18日": [
        "英語長文",
        "英語Wt",
        "数Ⅱ S/Lb"
    ],
    "5月25日": [
        "G2",
        "数Ⅱ S/La",
        "E2",
        "現代文",
        "A2"
    ],
    "5月26日": [
        "A2",
        "E2",
        "英語W",
        "K2",
        "英語長文"
    ],
    "5月27日": [
        "K1",
        "G1",
        "英語R",
        "英語Wt",
        "数Ⅱ S/Lb"
    ],
    "5月30日": [
        "数Ⅱ S/Lb",
        "英語長文",
        "古典"
    ],
    "6月1日": [
        "K2",
        "数Ⅱ S/La",
        "英語長文",
        "G1",
        "E2"
    ],
    "6月2日": [
        "A2",
        "E1",
        "IBA Ⅳ",
        "K2",
        "古典"
    ],
    "6月3日": [
        "G1",
        "数Ⅱ S/Lb",
        "K1",
        "体育別修",
        "英語R"
    ],
    "6月4日": [
        "古典",
        "現代文",
        "A1",
        "体育共修",
        "HR"
    ],
    "6月5日": [
        "数Ⅱ S/La",
        "E1",
        "A1",
        "英語W",
        "G2"
    ],
    "6月6日": [
        "英語長文",
        "体育共修",
        "古典"
    ],
    "6月8日": [
        "G2",
        "数Ⅱ S/La",
        "E2",
        "現代文",
        "A2"
    ],
    "6月9日": [
        "A2",
        "E2",
        "英語W",
        "K2",
        "英語長文"
    ],
    "6月10日": [
        "K1",
        "G1",
        "英語R",
        "英語Wt",
        "数Ⅱ S/Lb"
    ],
    "6月11日": [
        "古典",
        "G2",
        "体育別修",
        "K1",
        "HR"
    ],
    "6月12日": [
        "現代文",
        "E1",
        "A1",
        "英語R",
        "数Ⅱ S/La"
    ],
    "6月15日": [
        "K2",
        "数Ⅱ S/La",
        "英語長文",
        "G1",
        "E2"
    ],
    "6月16日": [
        "A2",
        "E1",
        "IBA Ⅳ",
        "K2",
        "古典"
    ],
    "6月17日": [
        "G1",
        "数Ⅱ S/Lb",
        "K1",
        "体育別修",
        "英語R"
    ],
    "6月18日": [
        "古典",
        "G2",
        "A1",
        "K1",
        "HR"
    ],
    "6月19日": [
        "数Ⅱ S/La",
        "E1",
        "A1",
        "英語W",
        "G2"
    ],
    "6月22日": [
        "G2",
        "数Ⅱ S/La",
        "E2",
        "現代文",
        "A2"
    ],
    "6月23日": [
        "A2",
        "E2",
        "英語W",
        "K2",
        "英語長文"
    ],
    "6月24日": [
        "G1",
        "数Ⅱ S/Lb",
        "K1",
        "体育別修",
        "英語R"
    ],
    "6月25日": [
        "古典",
        "G2",
        "体育別修",
        "K1",
        "HR"
    ],
    "6月26日": [
        "現代文",
        "E1",
        "A1",
        "英語R",
        "数Ⅱ S/La"
    ],
    "6月27日": [
        "数Ⅱ S/Lb",
        "英語長文",
        "体育共修"
    ],
    "6月29日": [
        "古典",
        "現代文",
        "E2",
        "体育共修",
        "HR"
    ],
    "6月30日": [
        "A2",
        "E1",
        "IBA Ⅳ",
        "K2",
        "古典"
    ],
    "7月1日": [
        "K1",
        "G2",
        "英語W"
    ],
    "7月9日": [
        "古典",
        "体育共修",
        "HR"
    ],
    "7月10日": [
        "数Ⅱ S/La",
        "E1",
        "A1"
    ],
    "7月13日": [
        "G2",
        "数Ⅱ S/La",
        "E2"
    ],
    "7月14日": [
        "A2",
        "K2",
        "英語長文"
    ],
    "7月15日": [
        "古典",
        "体育別修",
        "英語R"
    ],
    "7月16日": [
        "G2",
        "英語W",
        "HR"
    ],
    "7月17日": [
        "K2",
        "G1",
        "E2"
    ],
    "8月19日": [
        "数Ⅱ S/Lb",
        "現代文",
        "A1"
    ],
    "8月24日": [
        "G2",
        "数Ⅱ S/La",
        "E2",
        "現代文",
        "A2"
    ],
    "8月25日": [
        "A2",
        "E2",
        "英語W",
        "K2",
        "英語長文"
    ],
    "8月26日": [
        "K1",
        "G1",
        "英語R",
        "英語Wt",
        "数Ⅱ S/Lb"
    ],
    "8月27日": [
        "数Ⅱ S/La",
        "E2",
        "英語W",
        "K1",
        "HR"
    ],
    "8月28日": [
        "現代文",
        "E1",
        "A1"
    ],
    "8月29日": [
        "英語長文",
        "体育共修",
        "古典"
    ],
    "8月31日": [
        "K2",
        "数Ⅱ S/La",
        "英語長文"
    ],
    "9月1日": [
        "A2",
        "E1",
        "古典"
    ],
    "9月2日": [
        "G1",
        "数Ⅱ S/Lb",
        "K1"
    ],
    "9月3日": [
        "数Ⅱ S/La",
        "IBA Ⅳ",
        "A1"
    ],
    "9月4日": [
        "英語長文",
        "A2",
        "英語R"
    ],
    "9月5日": [
        "数Ⅱ S/Lb",
        "体育共修",
        "古典"
    ],
    "9月9日": [
        "K1",
        "G1",
        "英語R",
        "英語Wt",
        "数Ⅱ S/Lb"
    ],
    "9月10日": [
        "古典",
        "G2",
        "体育別修",
        "K1",
        "HR"
    ],
    "9月11日": [
        "現代文",
        "E1",
        "A1",
        "英語R",
        "現代文"
    ],
    "9月14日": [
        "K2",
        "数Ⅱ S/La",
        "英語長文",
        "G1",
        "E2"
    ],
    "9月15日": [
        "A2",
        "E1",
        "IBA Ⅳ",
        "K2",
        "古典"
    ],
    "9月16日": [
        "G1",
        "数Ⅱ S/Lb",
        "K1",
        "体育別修",
        "英語R"
    ],
    "9月17日": [
        "古典",
        "現代文",
        "A1",
        "体育共修",
        "HR"
    ],
    "9月18日": [
        "数Ⅱ S/La",
        "E1",
        "A1",
        "英語W",
        "G2"
    ],
    "9月24日": [
        "古典",
        "G2",
        "K2"
    ]
}